excel_helper/__init__.py
excel_helper/excel_helper.py
excel_helper-1.0.0.dist-info/LICENSE
excel_helper-1.0.0.dist-info/METADATA
excel_helper-1.0.0.dist-info/WHEEL
excel_helper-1.0.0.dist-info/top_level.txt
excel_helper-1.0.0.dist-info/RECORD
