Metadata-Version: 2.1
Name: excel-helper
Version: 1.0.0
Summary: A simple library to simplify Excel manipulation using openpyxl
Home-page: https://github.com/rahulgurujala/excel-helper
Author: Rahul Gurujala
Author-email: isaacnewtonrahul@gmail.com
License: UNKNOWN
Platform: UNKNOWN
Classifier: Development Status :: 3 - Alpha
Classifier: Intended Audience :: Developers
Classifier: License :: OSI Approved :: MIT License
Classifier: Operating System :: OS Independent
Classifier: Programming Language :: Python :: 3
Classifier: Programming Language :: Python :: 3.6
Classifier: Programming Language :: Python :: 3.7
Classifier: Programming Language :: Python :: 3.8
Classifier: Programming Language :: Python :: 3.9
Classifier: Programming Language :: Python :: 3.10
Requires-Python: >=3.6
License-File: LICENSE
Requires-Dist: openpyxl>=3.0.0
Requires-Dist: pandas>=2.2.2
Requires-Dist: Jinja2>=3.1.4
